oblig2/fulladder.vhd
library IEEE; 
use IEEE.STD_LOGIC_1164.all;

entity fulladder is
    port(a, b, cin: in std_logic;
          s, cout: out std_logic);
end;

architecture synth of fulladder is
begin
    s <= (a xor b) xor cin;
    cout <= ((a xor b) and cin) or (a and b);
end;

oblig2/cla_block.vhd
library IEEE; 
use IEEE.STD_LOGIC_1164.all;

entity CLA_block is
  port(
    a, b  : in  std_logic_vector(3 downto 0);
    cin   : in  std_logic;
    s     : out std_logic_vector(3 downto 0);
    cout  : out std_logic
  );
end entity CLA_block;

architecture mixed of CLA_block is
    component fulladder
        port(a, b, cin: in std_logic;
             s, cout: out std_logic);
    end component;

    signal p, g: std_logic_vector(3 downto 0);
    signal c: std_logic_vector(4 downto 0);
    signal p30, g30: std_logic;

    begin
      p <= a or b;
      g <= a and b;
      p30 <= and p; --- p(0) and p(1) and p(2) and p(3)
      g30 <= (((((g(0) and p(1)) or g(1)) and p(2)) or g(2)) and p(3)) or g(3);
      cout <= g30 or (p30 and cin);

      c(0) <= cin;
      
      F1: fulladder 
      port map(
        a => a(0), 
        b => b(0), 
        cin => c(0), 
        s => s(0),
        cout => c(1)
      );

      F2: fulladder 
      port map(
        a => a(1), 
        b => b(1), 
        cin => c(1), 
        s => s(1),
        cout => c(2)
      );

      F3: fulladder 
      port map(
        a => a(2), 
        b => b(2), 
        cin => c(2), 
        s => s(2),
        cout => c(3)
      );

      F4: fulladder 
      port map(
        a => a(3), 
        b => b(3), 
        cin => c(3), 
        s => s(3),
        cout => c(4)
      ); 
end architecture mixed;

oblig2/cla_top.vhd
library IEEE; 
  use IEEE.STD_LOGIC_1164.all;

entity CLA_top is   
  generic(
    width : positive := 32
  );
  port(
    a, b  : in  std_logic_vector(width-1 downto 0);
    cin   : in  std_logic;
    s   : out std_logic_vector(width-1 downto 0);
    cout  : out std_logic
  );
end entity CLA_top;

architecture mixed of CLA_top is
    component CLA_block
    port(
        a, b  : in  std_logic_vector(3 downto 0);
        cin   : in  std_logic;
        s   : out std_logic_vector(3 downto 0);
        cout  : out std_logic
    );
    end component;

    signal c : std_logic_vector(width/4 - 1 downto 0);

    begin
    CLA1 : CLA_block
    port map(
        a => a(3 downto 0),
        b => b(3 downto 0),
        cin => cin,
        s => s(3 downto 0),
        cout => c(0)
    );
    CLA2 : CLA_block
    port map(
        a => a(7 downto 4),
        b => b(7 downto 4),
        cin => c(0),
        s => s(7 downto 4),
        cout => c(1)
    );
    CLA3 : CLA_block
    port map(
        a => a(11 downto 8),
        b => b(11 downto 8),
        cin => c(1),
        s => s(11 downto 8),
        cout => c(2)
    );
    CLA4 : CLA_block
    port map(
        a => a(15 downto 12),
        b => b(15 downto 12),
        cin => c(2),
        s => s(15 downto 12),
        cout => c(3)
    );
    CLA5 : CLA_block
    port map(
        a => a(19 downto 16),
        b => b(19 downto 16),
        cin => c(3),
        s => s(19 downto 16),
        cout => c(4)
    );
    CLA6 : CLA_block
    port map(
        a => a(23 downto 20),
        b => b(23 downto 20),
        cin => c(4),
        s => s(23 downto 20),
        cout => c(5)
    );
    CLA7 : CLA_block
    port map(
        a => a(27 downto 24),
        b => b(27 downto 24),
        cin => c(5),
        s => s(27 downto 24),
        cout => c(6)
    );
    CLA8 : CLA_block
    port map(
        a => a(31 downto 28),
        b => b(31 downto 28),
        cin => c(6),
        s => s(31 downto 28),
        cout => c(7)
    );
    cout <= c(width/4 - 1);

end architecture mixed;

oblig2/tb_cla_top.vhd
library IEEE; 
use IEEE.STD_LOGIC_1164.all;
  
entity tb_cla_top is   
end entity tb_cla_top;

architecture behavioral of tb_cla_top is 
  component CLA_top is
    generic(
    width : positive := 32
    );
    port(
        a, b  : in  std_logic_vector(width-1 downto 0);
        cin   : in  std_logic;
        s   : out std_logic_vector(width-1 downto 0);
        cout  : out std_logic
    );
  end component;

  signal tb_a, tb_b : std_logic_vector(31 downto 0) := (others => '0');
  signal tb_cin : std_logic := '0';
  signal tb_s : std_logic_vector(31 downto 0);
  signal tb_cout : std_logic;
	  
begin  
  DUT: CLA_top   
  port map(        
    a    => tb_a,   
    b    => tb_b,   
    cin  => tb_cin, 
    s  => tb_s,   
    cout => tb_cout 
  );
  	
  process  
  begin
    wait for 10 ns;
    tb_a <= "00000000000000000000000000000000";
    tb_b <= "00000000000000000000000000000000";
    tb_cin <= '0';
    wait for 10 ns;
    assert(tb_s = "00000000000000000000000000000000") report ("test1: tb_s feil") severity failure;
    assert(tb_cout = '0') report ("test1: tb_cout feil") severity failure;

    tb_a <= "00000000000000000000000000000000";
    tb_b <= "00000000000000000000000000000001";
    tb_cin <= '0';
    wait for 10 ns;
    assert(tb_s = "00000000000000000000000000000001") report ("test2: tb_s feil") severity failure;
    assert(tb_cout = '0') report ("test2: tb_cout feil") severity failure;

    tb_a <= "00000000000000000000000000000001";
    tb_b <= "00000000000000000000000000000001";
    tb_cin <= '1';
    wait for 10 ns;
    assert(tb_s = "00000000000000000000000000000011") report ("test3: tb_s feil") severity failure;
    assert(tb_cout = '0') report ("test3: tb_cout feil") severity failure;

    tb_a <= "11111111111111111111111111111111";
    tb_b <= "00000000000000000000000000000001";
    tb_cin <= '0';
    wait for 10 ns;
    assert(tb_s = "00000000000000000000000000000000") report ("test4: tb_s feil") severity failure;
    assert(tb_cout = '1') report ("test4: tb_cout feil") severity failure;

    tb_a <= "11111111111111111111111111111111";
    tb_b <= "11111111111111111111111111111111";
    tb_cin <= '1';
    wait for 10 ns;
    assert(tb_s = "11111111111111111111111111111111") report ("test5: tb_s feil") severity failure;
    assert(tb_cout = '1') report ("test5: tb_cout feil") severity failure;

    tb_a <= "10000000000000000000000000000000";
    tb_b <= "10000000000000000000000000000000";
    tb_cin <= '0';
    wait for 10 ns;
    assert(tb_s = "00000000000000000000000000000000") report ("test6: tb_s feil") severity failure;
    assert(tb_cout = '1') report ("test6: tb_cout feil") severity failure;

    tb_a <= "01010101010101010101010101010101";
    tb_b <= "00110011001100110011001100110011";
    tb_cin <= '0';
    wait for 10 ns;
    assert(tb_s = "10000110000001100110100001110111") report ("test7: tb_s feil") severity failure;
    assert(tb_cout = '0') report ("test7: tb_cout feil") severity failure;

    tb_a <= "11111111111111111111111111110000";
    tb_b <= "00000000000000000000000000001111";
    tb_cin <= '0';
    wait for 10 ns;
    assert(tb_s = "11111111111111111111111111111111") report ("test8: tb_s feil") severity failure;
    assert(tb_cout = '0') report ("test8: tb_cout feil") severity failure;


    tb_a <= "11111111111111111111111111111111";
    tb_b <= "11111111111111111111111111111111";
    tb_cin <= '0';
    wait for 10 ns;
    assert(tb_s = "11111111111111111111111111111110") report ("test9: tb_cout feil") severity failure;
    assert(tb_cout = '1') report ("test9: tb_cout feil") severity failure;

    tb_a <= "00000000000000000000000000000001";
    tb_b <= "00000000000000000000000000000001";
    tb_cin <= '0';
    wait for 10 ns;
    assert(tb_s = "00000000000000000000000000000010") report ("test10: tb_s feil") severity failure;
    assert(tb_cout = '0') report ("test10: tb_cout feil") severity failure;

    report("Ferdig!") severity note;
    std.env.stop;   
  end process;
end architecture behavioral;

oblig2/cla_top.vcd
$date
	Mon Sep 30 20:34:59 2024
$end
$version
	QuestaSim Version 2020.4
$end
$timescale
	1fs
$end
$scope module tb_cla_top $end
$var wire 1 ! tb_a [31] $end
$var wire 1 " tb_a [30] $end
$var wire 1 # tb_a [29] $end
$var wire 1 $ tb_a [28] $end
$var wire 1 % tb_a [27] $end
$var wire 1 & tb_a [26] $end
$var wire 1 ' tb_a [25] $end
$var wire 1 ( tb_a [24] $end
$var wire 1 ) tb_a [23] $end
$var wire 1 * tb_a [22] $end
$var wire 1 + tb_a [21] $end
$var wire 1 , tb_a [20] $end
$var wire 1 - tb_a [19] $end
$var wire 1 . tb_a [18] $end
$var wire 1 / tb_a [17] $end
$var wire 1 0 tb_a [16] $end
$var wire 1 1 tb_a [15] $end
$var wire 1 2 tb_a [14] $end
$var wire 1 3 tb_a [13] $end
$var wire 1 4 tb_a [12] $end
$var wire 1 5 tb_a [11] $end
$var wire 1 6 tb_a [10] $end
$var wire 1 7 tb_a [9] $end
$var wire 1 8 tb_a [8] $end
$var wire 1 9 tb_a [7] $end
$var wire 1 : tb_a [6] $end
$var wire 1 ; tb_a [5] $end
$var wire 1 < tb_a [4] $end
$var wire 1 = tb_a [3] $end
$var wire 1 > tb_a [2] $end
$var wire 1 ? tb_a [1] $end
$var wire 1 @ tb_a [0] $end
$var wire 1 A tb_b [31] $end
$var wire 1 B tb_b [30] $end
$var wire 1 C tb_b [29] $end
$var wire 1 D tb_b [28] $end
$var wire 1 E tb_b [27] $end
$var wire 1 F tb_b [26] $end
$var wire 1 G tb_b [25] $end
$var wire 1 H tb_b [24] $end
$var wire 1 I tb_b [23] $end
$var wire 1 J tb_b [22] $end
$var wire 1 K tb_b [21] $end
$var wire 1 L tb_b [20] $end
$var wire 1 M tb_b [19] $end
$var wire 1 N tb_b [18] $end
$var wire 1 O tb_b [17] $end
$var wire 1 P tb_b [16] $end
$var wire 1 Q tb_b [15] $end
$var wire 1 R tb_b [14] $end
$var wire 1 S tb_b [13] $end
$var wire 1 T tb_b [12] $end
$var wire 1 U tb_b [11] $end
$var wire 1 V tb_b [10] $end
$var wire 1 W tb_b [9] $end
$var wire 1 X tb_b [8] $end
$var wire 1 Y tb_b [7] $end
$var wire 1 Z tb_b [6] $end
$var wire 1 [ tb_b [5] $end
$var wire 1 \ tb_b [4] $end
$var wire 1 ] tb_b [3] $end
$var wire 1 ^ tb_b [2] $end
$var wire 1 _ tb_b [1] $end
$var wire 1 ` tb_b [0] $end
$var wire 1 a tb_cin $end
$var wire 1 b tb_s [31] $end
$var wire 1 c tb_s [30] $end
$var wire 1 d tb_s [29] $end
$var wire 1 e tb_s [28] $end
$var wire 1 f tb_s [27] $end
$var wire 1 g tb_s [26] $end
$var wire 1 h tb_s [25] $end
$var wire 1 i tb_s [24] $end
$var wire 1 j tb_s [23] $end
$var wire 1 k tb_s [22] $end
$var wire 1 l tb_s [21] $end
$var wire 1 m tb_s [20] $end
$var wire 1 n tb_s [19] $end
$var wire 1 o tb_s [18] $end
$var wire 1 p tb_s [17] $end
$var wire 1 q tb_s [16] $end
$var wire 1 r tb_s [15] $end
$var wire 1 s tb_s [14] $end
$var wire 1 t tb_s [13] $end
$var wire 1 u tb_s [12] $end
$var wire 1 v tb_s [11] $end
$var wire 1 w tb_s [10] $end
$var wire 1 x tb_s [9] $end
$var wire 1 y tb_s [8] $end
$var wire 1 z tb_s [7] $end
$var wire 1 { tb_s [6] $end
$var wire 1 | tb_s [5] $end
$var wire 1 } tb_s [4] $end
$var wire 1 ~ tb_s [3] $end
$var wire 1 !! tb_s [2] $end
$var wire 1 "! tb_s [1] $end
$var wire 1 #! tb_s [0] $end
$var wire 1 $! tb_cout $end
$upscope $end
$enddefinitions $end
#0
0!
0"
0#
0$
0%
0&
0'
0(
0)
0*
0+
0,
0-
0.
0/
00
01
02
03
04
05
06
07
08
09
0:
0;
0<
0=
0>
0?
0@
0A
0B
0C
0D
0E
0F
0G
0H
0I
0J
0K
0L
0M
0N
0O
0P
0Q
0R
0S
0T
0U
0V
0W
0X
0Y
0Z
0[
0\
0]
0^
0_
0`
0a
0b
0c
0d
0e
0f
0g
0h
0i
0j
0k
0l
0m
0n
0o
0p
0q
0r
0s
0t
0u
0v
0w
0x
0y
0z
0{
0|
0}
0~
0!!
0"!
0#!
0$!
0b
0c
0d
0f
0g
0h
0j
0k
0l
0n
0o
0p
0r
0s
0t
0v
0w
0x
0z
0{
0|
0~
0!!
0"!
0#!
0$!
0e
0i
0m
0q
0u
0y
0}
#30000000
1`
1#!
#50000000
1a
1@
1#!
1"!
#70000000
0a
1!
1"
1#
1$
1%
1&
1'
1(
1)
1*
1+
1,
1-
1.
1/
10
11
12
13
14
15
16
17
18
19
1:
1;
1<
1=
1>
1?
0b
0c
0d
0e
0f
0g
0h
0i
0j
0k
0l
0m
0n
0o
0p
0q
0r
0s
0t
0u
0v
0w
0x
0y
0z
0{
0|
0}
0~
0!!
0"!
0#!
1$!
#90000000
1a
1A
1B
1C
1D
1E
1F
1G
1H
1I
1J
1K
1L
1M
1N
1O
1P
1Q
1R
1S
1T
1U
1V
1W
1X
1Y
1Z
1[
1\
1]
1^
1_
1b
1c
1d
1e
1f
1g
1h
1i
1j
1k
1l
1m
1n
1o
1p
1q
1r
1s
1t
1u
1v
1w
1x
1y
1z
1{
1|
1}
1~
1!!
1"!
1#!
#110000000
0a
0B
0C
0D
0E
0F
0G
0H
0I
0J
0K
0L
0M
0N
0O
0P
0Q
0R
0S
0T
0U
0V
0W
0X
0Y
0Z
0[
0\
0]
0^
0_
0`
0"
0#
0$
0%
0&
0'
0(
0)
0*
0+
0,
0-
0.
0/
00
01
02
03
04
05
06
07
08
09
0:
0;
0<
0=
0>
0?
0@
0b
0c
0d
0f
0g
0h
0j
0k
0l
0n
0o
0p
0r
0s
0t
0v
0w
0x
0z
0{
0|
0~
0!!
0"!
0#!
0e
0i
0m
0q
0u
0y
0}
#130000000
0A
1C
1D
1G
1H
1K
1L
1O
1P
1S
1T
1W
1X
1[
1\
1_
1`
0!
1"
1$
1&
1(
1*
1,
1.
10
12
14
16
18
1:
1<
1>
1@
0c
0d
0g
0h
0k
0l
0o
0p
0s
0t
0w
0x
0{
0|
0!!
0"!
0$!
1b
1f
1j
1n
1r
1v
1z
1~
#150000000
0C
0D
0G
0H
0K
0L
0O
0P
0S
0T
0W
0X
0[
0\
1]
1^
1!
1#
1%
1'
1)
1+
1-
1/
11
13
15
17
19
1;
0>
0@
1b
1e
1f
1i
1j
1m
1n
1q
1r
1u
1v
1y
1z
1}
1~
1#!
1d
1h
1l
1p
1t
1x
1|
1"!
1c
1g
1k
1o
1s
1w
1{
1!!
#170000000
1A
1B
1C
1D
1E
1F
1G
1H
1I
1J
1K
1L
1M
1N
1O
1P
1Q
1R
1S
1T
1U
1V
1W
1X
1Y
1Z
1[
1\
1=
1>
1?
1@
1b
1c
1d
1e
1f
1g
1h
1i
1j
1k
1l
1m
1n
1o
1p
1q
1r
1s
1t
1u
1v
1w
1x
1y
1z
1{
1|
1}
1~
1!!
1"!
0#!
1$!
#190000000
0A
0B
0C
0D
0E
0F
0G
0H
0I
0J
0K
0L
0M
0N
0O
0P
0Q
0R
0S
0T
0U
0V
0W
0X
0Y
0Z
0[
0\
0]
0^
0_
0!
0"
0#
0$
0%
0&
0'
0(
0)
0*
0+
0,
0-
0.
0/
00
01
02
03
04
05
06
07
08
09
0:
0;
0<
0=
0>
0?
0b
0c
0d
0f
0g
0h
0j
0k
0l
0n
0o
0p
0r
0s
0t
0v
0w
0x
0z
0{
0|
0~
0!!
0$!
0e
0i
0m
0q
0u
0y
0}
